triton_shared/__init__.py
triton_shared/base.py
triton_shared/py.typed
triton_shared/schemas/__init__.py
triton_shared/schemas/_all_models_gen.py
triton_shared/schemas/auth/__init__.py
triton_shared/schemas/fleet/__init__.py
triton_shared/schemas/tenants/__init__.py
triton_shared/schemas/users/__init__.py
triton_shared-0.1.11.dist-info/licenses/LICENSE
triton_shared-0.1.11.dist-info/METADATA
triton_shared-0.1.11.dist-info/WHEEL
triton_shared-0.1.11.dist-info/top_level.txt
triton_shared-0.1.11.dist-info/RECORD
