Metadata-Version: 2.4
Name: triton-shared
Version: 0.1.11
Summary: Shared schemas, types, and constants for Boat Fix Triton.
Author-email: Boat Fix <chris@ridenauta.com>
License: Proprietary
Project-URL: Homepage, https://github.com/shen3443/boatfix-triton-shared
Requires-Python: >=3.10
License-File: LICENSE
Requires-Dist: pydantic<3.0,>=2.5
Dynamic: license-file
